argstruct/__init__.py
argstruct/argparse_module.py
argstruct/argparse_object.py
argstruct/argparser_ng_module.py
argstruct/argparser_ng_object.py
argstruct/documentation.py
argstruct/object.py
argstruct/specs/DO_NOT_EDIT_THESE.md
argstruct/specs/argmap.command.args-root.spec
argstruct/specs/argmap.command.args.spec
argstruct/specs/argmap.command.spec
argstruct/specs/argmap.commands.spec
argstruct/specs/argmap.root.spec
argstruct-1.2.0.dist-info/licenses/LICENSE.md
argstruct-1.2.0.dist-info/METADATA
argstruct-1.2.0.dist-info/WHEEL
argstruct-1.2.0.dist-info/entry_points.txt
argstruct-1.2.0.dist-info/top_level.txt
argstruct-1.2.0.dist-info/RECORD
