Metadata-Version: 2.4
Name: argstruct
Version: 1.2.0
Summary: Reusable Argument Structure
Author-email: AccidentallyTheCable <cableninja@cableninja.net>
License: GPLv3
Project-URL: Homepage, https://gitlab.com/accidentallythecable-public/python-modules/python-argstruct/
Project-URL: Bug Tracker, https://gitlab.com/accidentallythecable-public/python-modules/python-argstruct/issues
Classifier: Programming Language :: Python :: 3
Classifier: License :: OSI Approved :: GNU General Public License v3 (GPLv3)
Classifier: Topic :: Software Development :: Libraries :: Python Modules
Classifier: Topic :: Software Development :: Libraries
Classifier: Topic :: Software Development :: Documentation
Classifier: Topic :: Documentation
Requires-Python: >=3.11
License-File: LICENSE.md
Requires-Dist: atckit<2.0,>=1.0
Requires-Dist: specker<2.0,>=1.0
Requires-Dist: deepmerge<=1.2.0,>=1.1.0
Requires-Dist: tabulate<1.0
Requires-Dist: types-tabulate<1.0
Dynamic: license-file
